redisipc/__init__.py
redisipc/ipc.py
redis_ipc-0.2.1.dist-info/LICENSE
redis_ipc-0.2.1.dist-info/METADATA
redis_ipc-0.2.1.dist-info/WHEEL
redis_ipc-0.2.1.dist-info/top_level.txt
redis_ipc-0.2.1.dist-info/RECORD
