Metadata-Version: 2.1
Name: redis-ipc
Version: 0.2.1
Summary: A minimal multi producer single consumer IPC using redis pub/sub
Home-page: https://github.com/AXVin/redis-ipc
Author: AXVin
License: AGPL v3
Keywords: aioredis,redis,ipc
Classifier: Development Status :: 5 - Production/Stable
Classifier: Natural Language :: English
Classifier: Intended Audience :: Developers
Classifier: Programming Language :: Python :: 3.8
Classifier: Programming Language :: Python :: 3.9
Classifier: Operating System :: OS Independent
Classifier: Topic :: Communications
Classifier: Topic :: Software Development :: Libraries
Classifier: Topic :: Software Development :: Libraries :: Python Modules
Classifier: Topic :: Utilities
Classifier: Typing :: Typed
Classifier: License :: OSI Approved :: GNU Affero General Public License v3 or later (AGPLv3+)
Requires-Python: >=3.8
License-File: LICENSE
Requires-Dist: aioredis (==2.0)
